setup.py
example/__init__.py
example/xiamiConsole.py
example/xiamiGUI.py
example/xiamiGuiZn.py
xiami/__init__.py
xiami/xiamiHttp.py
xiami/xiamiParse.py
xiami.egg-info/PKG-INFO
xiami.egg-info/SOURCES.txt
xiami.egg-info/dependency_links.txt
xiami.egg-info/top_level.txt