Metadata-Version: 1.0
Name: xiami
Version: 0.0.3
Summary: This is a xiami music download clinet
Home-page: https://rsj217.github.io/
Author: rsj217
Author-email: rsj217@gmail.com
License: MIT License
Keywords: xiami,music,download
Platform: any
